gradescope/__init__.py
gradescope/constants.py
gradescope/dataclass.py
gradescope/errors.py
gradescope/gradescope.py
gradescope/utils.py
gradescope_tool-0.1.4.dist-info/licenses/LICENSE
gradescope_tool-0.1.4.dist-info/METADATA
gradescope_tool-0.1.4.dist-info/WHEEL
gradescope_tool-0.1.4.dist-info/top_level.txt
gradescope_tool-0.1.4.dist-info/RECORD
