Metadata-Version: 2.4
Name: gradescope-tool
Version: 0.1.4
Summary: A Python wrapper for Gradescope to easily retrieve data from your Gradescope Courses.
Home-page: https://github.com/Teaching-and-Learning-in-Computing/Gradescope
Author: HyunJun Park, Daniel Song
Author-email: HyunJun Park <hyunjup4@uci.edu>, Daniel Song <djsong1@uci.edu>
License-Expression: MIT
Project-URL: Homepage, https://github.com/Teaching-and-Learning-in-Computing/Gradescope
Project-URL: Repository, https://github.com/Teaching-and-Learning-in-Computing/Gradescope
Project-URL: Issues, https://github.com/Teaching-and-Learning-in-Computing/Gradescope/issues
Classifier: Programming Language :: Python :: 3
Classifier: Operating System :: OS Independent
Requires-Python: >=3.7
License-File: LICENSE
Requires-Dist: beautifulsoup4
Requires-Dist: pandas
Requires-Dist: Requests
Dynamic: author
Dynamic: home-page
Dynamic: license-file
Dynamic: requires-python
